finext/__init__.py
finext/co_study.py
finext/co_tools.py
finext-1.0.3.dist-info/licenses/LICENSE
finext-1.0.3.dist-info/METADATA
finext-1.0.3.dist-info/WHEEL
finext-1.0.3.dist-info/top_level.txt
finext-1.0.3.dist-info/RECORD
