Metadata-Version: 2.4
Name: finext
Version: 1.0.3
Summary: extension tools of finlab
Author-email: Hung-Ching-Lee <f1289308470@gmail.com>
License: MIT
Project-URL: Homepage, https://github.com/Hung-Ching-Lee/finlab_exten?tab=readme-ov-file
Project-URL: Issues, https://github.com/pypa/sampleproject/issues
Classifier: Programming Language :: Python :: 3
Classifier: Operating System :: OS Independent
Requires-Python: >=3.10
License-File: LICENSE
Dynamic: license-file
